{
  "type": "map",
  "events": {
    "2": {
      "0": [
        {
          "type": "text",
          "text": [
            "氷の妖精",
            "ルナロアちゃんはどうしたの？",
            "\\!えっと、まさか別れちゃった…？"
          ],
          "pointer": [
            0,
            1,
            2
          ],
          "meta": "101code"
        }
      ],
      "1": [
        {
          "type": "text",
          "text": [
            "氷の妖精",
            "きゃー♡\\. ルナロアちゃーん♡",
            "\\!…ちっ。\\.こいつがいなけりゃなぁ…。"
          ],
          "pointer": [
            0,
            1,
            2
          ],
          "meta": "101code"
        }
      ]
    },
    "7": {
      "0": [
        {
          "type": "text",
          "text": [
            "氷の妖精",
            "よく…おいでになりました。",
            "ここが『氷の試練』の最奥になります…。"
          ],
          "pointer": [
            8,
            9,
            10
          ],
          "meta": "101code"
        },
        {
          "type": "text",
          "text": [
            "氷の妖精",
            "適応者は、あなた…\\.ですね。",
            "\\!少しこちらに来て……\\.お顔を拝見しても…？"
          ],
          "pointer": [
            12,
            13,
            14
          ],
          "meta": "101code"
        },
        {
          "type": "text",
          "text": [
            "ルナロア",
            "\\SE[2]は、\\.はい……。"
          ],
          "pointer": [
            16,
            17
          ],
          "meta": "101code"
        },
        {
          "type": "text",
          "text": [
            "氷の妖精",
            "まぁ……。"
          ],
          "pointer": [
            26,
            27
          ],
          "meta": "101code"
        },
        {
          "type": "text",
          "text": [
            "氷の妖精",
            "まぁ、\\.まぁまぁ……！！"
          ],
          "pointer": [
            29,
            30
          ],
          "meta": "101code"
        },
        {
          "type": "text",
          "text": [
            "氷の妖精",
            "あーん♡ \\.可愛いー！！",
            "\\.幼さを残した顔立ちに大人びた長い髪…。",
            "\\!お姉さん。きゅんきゅんしちゃう…！"
          ],
          "pointer": [
            35,
            36,
            37,
            38
          ],
          "meta": "101code"
        },
        {
          "type": "text",
          "text": [
            "ルナロア",
            "\\SE[2]えっ。"
          ],
          "pointer": [
            40,
            41
          ],
          "meta": "101code"
        },
        {
          "type": "text",
          "text": [
            "氷の妖精",
            "あなた…とっても強いでしょ…？",
            "\\!私ね、そういう娘をしっかり",
            "『調教』して『奴隷』にするのが好きなの…。"
          ],
          "pointer": [
            48,
            49,
            50,
            51
          ],
          "meta": "101code"
        },
        {
          "type": "text",
          "text": [
            "氷の妖精",
            "最初は悔しそうなんだけどね…。",
            "\\!最後には自分からおねだり出来るようになって…。",
            "\\!そのギャップがたまらないの…♡"
          ],
          "pointer": [
            52,
            53,
            54,
            55
          ],
          "meta": "101code"
        },
        {
          "type": "text",
          "text": [
            "氷の妖精",
            "ねぇ \\.私の『奴隷』にならない…？",
            "\\!大丈夫…怖くなんてないわ。",
            "すぐに私なしじゃ、いられなくなるから…♡"
          ],
          "pointer": [
            56,
            57,
            58,
            59
          ],
          "meta": "101code"
        },
        {
          "type": "text",
          "text": [
            "ルナロア",
            "\\SE[4]えっ…いやっ。",
            "\\.私はですね……。"
          ],
          "pointer": [
            61,
            62,
            63
          ],
          "meta": "101code"
        },
        {
          "type": "text",
          "text": [
            "ラウラ",
            "\\SE[19]ちょっと…！！",
            "\\.そういうのやめてください！！",
            "\\!\\SE[17]とっても、迷惑なんですけど…！！？"
          ],
          "pointer": [
            80,
            81,
            82,
            83
          ],
          "meta": "101code"
        },
        {
          "type": "text",
          "text": [
            "ラウラ",
            "\\SE[60]っていうか、『解釈違い』です！！",
            "\\!\\SE[100]私のルナは誰にも負けない",
            "『最強の幼馴染』なんですっ…！！"
          ],
          "pointer": [
            84,
            85,
            86,
            87
          ],
          "meta": "101code"
        },
        {
          "type": "text",
          "text": [
            "氷の妖精",
            "ちょっと…なによ、あんた…？",
            "\\!私の『恋人』に触らないでくれる？"
          ],
          "pointer": [
            89,
            90,
            91
          ],
          "meta": "101code"
        },
        {
          "type": "text",
          "text": [
            "ラウラ",
            "\\SE[123]こ…\\.こっ……！！",
            "\\.『恋人ぉ』！！！！！",
            "\\!\\SE[102]言うに事欠いてこのアマ…！！"
          ],
          "pointer": [
            92,
            93,
            94,
            95
          ],
          "meta": "101code"
        },
        {
          "type": "text",
          "text": [
            "氷の妖精",
            "じゃあ何？",
            "あんたはこの娘のなんだっていうのよ？"
          ],
          "pointer": [
            98,
            99,
            100
          ],
          "meta": "101code"
        },
        {
          "type": "text",
          "text": [
            "ラウラ",
            "\\SE[102]私がルナの『恋人』です！！",
            "\\.彼女が望めば私は『奴隷』にだってなるんです！！",
            "\\!\\SE[40]だから！\\! あなたに！！\\! 『枠』なんてないんです！！！"
          ],
          "pointer": [
            101,
            102,
            103,
            104
          ],
          "meta": "101code"
        },
        {
          "type": "text",
          "text": [
            "ルナロア",
            "\\SE[11]（やった。\\.『言質』とったわ。）"
          ],
          "pointer": [
            109,
            110
          ],
          "meta": "101code"
        },
        {
          "type": "text",
          "text": [
            "氷の妖精",
            "ふーーーん？ そう？",
            "\\!じゃあ、あんたがいなくなれば",
            "\\.私を邪魔するものは『消える』ってことね？"
          ],
          "pointer": [
            116,
            117,
            118,
            119
          ],
          "meta": "101code"
        },
        {
          "type": "text",
          "text": [
            "ラウラ",
            "\\SE[102]お前なんかに…\\.私がやられるもんですか…！！"
          ],
          "pointer": [
            124,
            125
          ],
          "meta": "101code"
        },
        {
          "type": "text",
          "text": [
            "氷の妖精",
            "矮小な『小娘』如き、\\.消し飛ばしてくれる…！"
          ],
          "pointer": [
            126,
            127
          ],
          "meta": "101code"
        },
        {
          "type": "text",
          "text": [
            "ラウラ",
            "\\SE[102]上等だ…！",
            "\\!\\SE[40]かかってこい…\\.『年増』っ…！！"
          ],
          "pointer": [
            128,
            129,
            130
          ],
          "meta": "101code"
        },
        {
          "type": "text",
          "text": [
            "ルナロア",
            "\\SE[21]あの…これ…。",
            "\\.私の『試練』なんだけど…。"
          ],
          "pointer": [
            138,
            139,
            140
          ],
          "meta": "101code"
        }
      ]
    }
  }
}