{
  "type": "map",
  "name": "",
  "events": {
    "11": {
      "0": [
        {
          "type": "text",
          "text": [
            "ティータ",
            "…そっち持った？\\. せーの…で、\\.いくのよ？",
            "\\!ちゃんと『タイミング』合わせてね？",
            "\\!それじゃ、\\!せーのっ…！！"
          ],
          "pointer": [
            17,
            18,
            19,
            20
          ],
          "meta": "101code"
        },
        {
          "type": "text",
          "text": [
            "アリス",
            "ふんっ…！！？"
          ],
          "pointer": [
            22,
            23
          ],
          "meta": "101code"
        },
        {
          "type": "text",
          "text": [
            "クローディア",
            "そっち持ち上げすぎっ…！！",
            "傾いてる、傾いてるっ！！"
          ],
          "pointer": [
            24,
            25,
            26
          ],
          "meta": "101code"
        },
        {
          "type": "text",
          "text": [
            "ヴィタ",
            "ぐぉ…！！！",
            "この、負けるかぁ！！！"
          ],
          "pointer": [
            28,
            29,
            30
          ],
          "meta": "101code"
        },
        {
          "type": "text",
          "text": [
            "キャット",
            "あっ、この辺りで『ストップ』ですー！",
            "それ以上いくと邪魔になっちゃいそうなのでー。"
          ],
          "pointer": [
            32,
            33,
            34
          ],
          "meta": "101code"
        },
        {
          "type": "text",
          "text": [
            "ニキータ",
            "ちょっと、右が傾いてるかな…？",
            "\\!クローディアちゃん。\\.少しだけ手前に出来る？"
          ],
          "pointer": [
            35,
            36,
            37
          ],
          "meta": "101code"
        },
        {
          "type": "text",
          "text": [
            "クローディア",
            "て、手前っ！？\\. こん、のぉ…！！"
          ],
          "pointer": [
            38,
            39
          ],
          "meta": "101code"
        },
        {
          "type": "text",
          "text": [
            "ティータ",
            "あっ、いい感じ…！",
            "\\!あとほんのちょっと右っ…！！"
          ],
          "pointer": [
            42,
            43,
            44
          ],
          "meta": "101code"
        },
        {
          "type": "text",
          "text": [
            "クローディア",
            "ほん、のっ、…\\.ちょっと……！！"
          ],
          "pointer": [
            48,
            49
          ],
          "meta": "101code"
        },
        {
          "type": "text",
          "text": [
            "破滅のアリス",
            "\\SE[1]わぁ…！！ \\.なんて素敵な黒光りっ！！",
            "私たち、やり遂げたんだね…！！",
            "\\!\\SE[15]とてつもない『達成感』を感じるわ！！"
          ],
          "pointer": [
            67,
            68,
            69,
            70
          ],
          "meta": "101code"
        },
        {
          "type": "text",
          "text": [
            "クローディア",
            "\\SE[24]はぁ…はぁ！！\\. 絶対におかしいっ……！！",
            "\\!\\SE[16]こんなの、『業者』がやることでしょう！！",
            "子供３人が『力任せ』でやることじゃないわ…！！"
          ],
          "pointer": [
            76,
            77,
            78,
            79
          ],
          "meta": "101code"
        },
        {
          "type": "text",
          "text": [
            "キャット",
            "\\SE[16]いやぁ…節約できましたね！\\. でも、すごいですよ！",
            "こんなの屈強な男でも出来ませんからねっ！！",
            "\\!\\SE[10]胸を張って、『誇り』にしていいと思いますよ！！"
          ],
          "pointer": [
            81,
            82,
            83,
            84
          ],
          "meta": "101code"
        },
        {
          "type": "text",
          "text": [
            "クローディア",
            "\\SE[14]そ、そうなの…？"
          ],
          "pointer": [
            87,
            88
          ],
          "meta": "101code"
        },
        {
          "type": "text",
          "text": [
            "ニキータ",
            "\\SE[1]ええっ、すごいわよ。",
            "\\!\\SE[45]あなたの能力として、自信を持っていいわ。"
          ],
          "pointer": [
            89,
            90,
            91
          ],
          "meta": "101code"
        },
        {
          "type": "text",
          "text": [
            "クローディア",
            "\\SE[0]……\\.……\\.……。\\!\\SE[48]"
          ],
          "pointer": [
            92,
            93
          ],
          "meta": "101code"
        },
        {
          "type": "text",
          "text": [
            "ラウラ",
            "\\SE[70]り、リビングにピアノ…！？",
            "なんで！？\\. どうして！！？"
          ],
          "pointer": [
            118,
            119,
            120
          ],
          "meta": "101code"
        },
        {
          "type": "text",
          "text": [
            "ルナロア",
            "\\SE[4]わぁ、すごーい！",
            "\\!\\SE[2]これは、誰かが買ったの…？",
            "\\!\\SE[3]でも、弾ける人なんていたかしら…？"
          ],
          "pointer": [
            121,
            122,
            123,
            124
          ],
          "meta": "101code"
        },
        {
          "type": "text",
          "text": [
            "ニキータ",
            "\\SE[26]えへへー…\\.それはねー……。"
          ],
          "pointer": [
            127,
            128
          ],
          "meta": "101code"
        },
        {
          "type": "text",
          "text": [
            "ベガ",
            "\\SE[60]騒がしいと思ったら…。",
            "\\!\\SE[82]なに…どうしちゃったの、\\.これ…？"
          ],
          "pointer": [
            151,
            152,
            153
          ],
          "meta": "101code"
        },
        {
          "type": "text",
          "text": [
            "ニキータ",
            "\\SE[46]聞いたわよー？",
            "ベガちゃんったら、『ピアノ』が弾けるんでしょ？",
            "\\!\\SE[15]だから『お姉さんマネー』で買っちゃった！！"
          ],
          "pointer": [
            155,
            156,
            157,
            158
          ],
          "meta": "101code"
        },
        {
          "type": "text",
          "text": [
            "ベガ",
            "\\SE[94]『ピアノ』を買った…！？"
          ],
          "pointer": [
            160,
            161
          ],
          "meta": "101code"
        },
        {
          "type": "text",
          "text": [
            "ルナロア",
            "\\SE[14]わっ、これは大人ねっ…！",
            "\\!\\SE[13]『大人買い』ってやつね……。"
          ],
          "pointer": [
            163,
            164,
            165
          ],
          "meta": "101code"
        },
        {
          "type": "text",
          "text": [
            "ベガ",
            "\\SE[18]……なんか、変に期待されてるみたいだけど。",
            "\\!\\SE[4]『ピアノ』なんて、何年も弾いてないし、",
            "人様に聞かせるほどのことは出来ないわよ？",
            "\\!\\SE[75]曲だって、ほとんど忘れてるし。"
          ],
          "pointer": [
            168,
            169,
            170,
            171,
            172
          ],
          "meta": "101code"
        },
        {
          "type": "text",
          "text": [
            "ニキータ",
            "\\SE[29]やだー！！\\. 聞きたいー！！",
            "なんでもいいから弾いてー！！",
            "\\!\\SE[14]ベガちゃんの素敵な所、見たいー！！"
          ],
          "pointer": [
            174,
            175,
            176,
            177
          ],
          "meta": "101code"
        },
        {
          "type": "text",
          "text": [
            "ベガ",
            "\\SE[22]子供かっ…！"
          ],
          "pointer": [
            178,
            179
          ],
          "meta": "101code"
        },
        {
          "type": "text",
          "text": [
            "レベッカ",
            "\\SE[14]何っ…！？",
            "今、お姉さまが『ピアノ』弾くって言った！？",
            "\\!\\SE[11]そんな『ビッグイベント』が起ころうとしてるの…！！？"
          ],
          "pointer": [
            210,
            211,
            212,
            213
          ],
          "meta": "101code"
        },
        {
          "type": "text",
          "text": [
            "ライアン",
            "\\SE[52]いやいや、『ノック』くらいしろよ。",
            "\\!\\SE[53]いくらここでも、",
            "いきなり『人んち』に入るのは失礼だろ…。"
          ],
          "pointer": [
            214,
            215,
            216,
            217
          ],
          "meta": "101code"
        },
        {
          "type": "text",
          "text": [
            "レベッカ",
            "\\SE[4]っていうか、『ピアノ』弾けるんですか！！",
            "\\!\\SE[24]どうして教えてくれなかったんですかー！？",
            "\\!\\SE[6]お姉さまが私に『隠し事』なんてっー！！"
          ],
          "pointer": [
            223,
            224,
            225,
            226
          ],
          "meta": "101code"
        },
        {
          "type": "text",
          "text": [
            "ベガ",
            "\\SE[82]いや、昔ちょっと弾いてたってだけで…。",
            "\\!\\SE[83]もう何年も『ブランク』があるし、",
            "別に、わざわざ言うような事でも…。"
          ],
          "pointer": [
            227,
            228,
            229,
            230
          ],
          "meta": "101code"
        },
        {
          "type": "text",
          "text": [
            "メリッサ",
            "\\SE[4]うわっ、なにこの『ピアノ』",
            "\\!\\SE[0]これから演奏会でも始まちゃう感じ…？"
          ],
          "pointer": [
            260,
            261,
            262
          ],
          "meta": "101code"
        },
        {
          "type": "text",
          "text": [
            "ロノア",
            "\\SE[1]ちょうよいいよいに、\\.ちたちゃん。"
          ],
          "pointer": [
            263,
            264
          ],
          "meta": "101code"
        },
        {
          "type": "text",
          "text": [
            "ベガ",
            "\\SE[92]うわっ、揃いも揃ってぞろぞろっと…。",
            "\\!\\SE[91]なにこの、かつてない人口密度は…。"
          ],
          "pointer": [
            268,
            269,
            270
          ],
          "meta": "101code"
        },
        {
          "type": "text",
          "text": [
            "キャット",
            "\\SE[16]いいじゃないですかー！！",
            "がんばって運んだんだし、聞きたいですよー！！",
            "\\!\\SE[14]みなさんだって、聞きたいですよねぇ…！？"
          ],
          "pointer": [
            271,
            272,
            273,
            274
          ],
          "meta": "101code"
        },
        {
          "type": "text",
          "text": [
            "レベッカ＆ニキータ",
            "聞きたーいっ！！！"
          ],
          "pointer": [
            283,
            284
          ],
          "meta": "101code"
        },
        {
          "type": "text",
          "text": [
            "クローディア",
            "\\SE[0]…ねぇ。",
            "この『ピアノ』っていうのはよく分からないけど…。",
            "\\!\\SE[3]聞いてた感じ、『音楽』に使うものなの？"
          ],
          "pointer": [
            291,
            292,
            293,
            294
          ],
          "meta": "101code"
        },
        {
          "type": "text",
          "text": [
            "ベガ",
            "\\SE[20]『ピアノ』の事は知らないのね…。",
            "\\!\\SE[3]…まぁ、大体合ってるけど。"
          ],
          "pointer": [
            295,
            296,
            297
          ],
          "meta": "101code"
        },
        {
          "type": "text",
          "text": [
            "クローディア",
            "\\SE[59]じゃあ、『ピアノ』の活躍は見たいわ。",
            "腕が引きちぎれるかと思いながら運んだんだもの。",
            "\\!\\SE[19]…この子の『晴れ舞台』は見ておきたい。"
          ],
          "pointer": [
            298,
            299,
            300,
            301
          ],
          "meta": "101code"
        },
        {
          "type": "text",
          "text": [
            "ルナロア",
            "\\SE[1]ベガ。この状況は弾くしかないわ。",
            "こんなに『頭数』が揃ってしまったんだもの。",
            "\\!\\SE[10]この場を収めるには、『一発』ぶちかますしかないわ。"
          ],
          "pointer": [
            307,
            308,
            309,
            310
          ],
          "meta": "101code"
        },
        {
          "type": "text",
          "text": [
            "ラウラ",
            "\\SE[44]たしかに、これはやるしかないかもね…。"
          ],
          "pointer": [
            313,
            314
          ],
          "meta": "101code"
        },
        {
          "type": "text",
          "text": [
            "ベガ",
            "\\SE[60]他人事だと思って好き勝手言って…。"
          ],
          "pointer": [
            317,
            318
          ],
          "meta": "101code"
        },
        {
          "type": "text",
          "text": [
            "ベガ",
            "\\SE[22]分かった、分かったわよ！！",
            "弾けばいいんでしょ、弾けばっ！！",
            "\\!\\SE[20]なまってても、文句言うんじゃないわよ！！"
          ],
          "pointer": [
            320,
            321,
            322,
            323
          ],
          "meta": "101code"
        },
        {
          "type": "text",
          "text": [
            "レベッカ＆ニキータ",
            "やったー！！"
          ],
          "pointer": [
            332,
            333
          ],
          "meta": "101code"
        },
        {
          "type": "text",
          "text": [
            "ベガ",
            "\\SE[60]なんで、こんなことに…。"
          ],
          "pointer": [
            361,
            362
          ],
          "meta": "101code"
        },
        {
          "type": "text",
          "text": [
            "キャット",
            "\\SE[1]あっ！\\. 昔聴かせてもらった曲が聞きたいです！！",
            "\\!\\SE[15]あの曲好きなんですよねー。",
            "若かりし当時に想いを馳せることが出来てー。"
          ],
          "pointer": [
            364,
            365,
            366,
            367
          ],
          "meta": "101code"
        },
        {
          "type": "text",
          "text": [
            "ベガ",
            "\\SE[2]じゃあ、別の曲にするわ。"
          ],
          "pointer": [
            368,
            369
          ],
          "meta": "101code"
        },
        {
          "type": "text",
          "text": [
            "ベガ",
            "\\SE[74]さて…。",
            "今の私が弾ける曲…\\.か。"
          ],
          "pointer": [
            385,
            386,
            387
          ],
          "meta": "101code"
        }
      ]
    },
    "14": {
      "0": [
        {
          "type": "text",
          "text": [
            "",
            "炎を見ていると心が落ち着いてくる。",
            "…ここの炎が一番ほっとする。"
          ],
          "pointer": [
            0,
            1,
            2
          ],
          "meta": "101code"
        }
      ]
    }
  }
}