{
  "type": "map",
  "name": "",
  "events": {
    "1": {
      "0": [
        {
          "type": "text",
          "text": [
            "",
            "演奏に集中しているようだ…。"
          ],
          "pointer": [
            0,
            1
          ],
          "meta": "101code"
        }
      ]
    },
    "5": {
      "0": [
        {
          "type": "text",
          "text": [
            "店主さん",
            "今度、『ユリシーン』の酒場で",
            "『バニーガールコラボ』を考えてるんだ。",
            "\\!よかったら、お嬢さんもどうだい？"
          ],
          "pointer": [
            0,
            1,
            2,
            3
          ],
          "meta": "101code"
        },
        {
          "type": "text",
          "text": [
            "ラウラ",
            "わ、私ですか…！？",
            "\\!いや、\\.ここまで過激なのはちょっと…。"
          ],
          "pointer": [
            4,
            5,
            6
          ],
          "meta": "101code"
        },
        {
          "type": "text",
          "text": [
            "ベガ",
            "ルナロアは好きそうだけどね。",
            "\\!こういう直球で『ハレンチ』なやつ。"
          ],
          "pointer": [
            7,
            8,
            9
          ],
          "meta": "101code"
        },
        {
          "type": "text",
          "text": [
            "ヴィタ",
            "あー…\\.好きそう。",
            "\\.ラウラも考えといた方がいいよ？"
          ],
          "pointer": [
            10,
            11,
            12
          ],
          "meta": "101code"
        },
        {
          "type": "text",
          "text": [
            "ラウラ",
            "えっ…！\\.えぇー……。"
          ],
          "pointer": [
            13,
            14
          ],
          "meta": "101code"
        }
      ],
      "1": [
        {
          "type": "text",
          "text": [
            "店主さん",
            "今度、『ユリシーン』の酒場で",
            "『バニーガールコラボ』を考えてるんだ。",
            "\\!よかったら、お嬢さんもどうだい？"
          ],
          "pointer": [
            0,
            1,
            2,
            3
          ],
          "meta": "101code"
        },
        {
          "type": "text",
          "text": [
            "ラウラ",
            "わ、私ですか…！？",
            "\\!いや、\\.ここまで過激なのはちょっと…。"
          ],
          "pointer": [
            4,
            5,
            6
          ],
          "meta": "101code"
        },
        {
          "type": "text",
          "text": [
            "ルナロア",
            "彼女の体型に合わせて",
            "『オーダメイド』で一着、頂けませんか？",
            "\\!言い値で買い取らせて頂きます。"
          ],
          "pointer": [
            7,
            8,
            9,
            10
          ],
          "meta": "101code"
        },
        {
          "type": "text",
          "text": [
            "ラウラ",
            "えっ…！\\.えぇー……。"
          ],
          "pointer": [
            11,
            12
          ],
          "meta": "101code"
        }
      ]
    },
    "6": {
      "0": [
        {
          "type": "text",
          "text": [
            "常連の戦士",
            "ここの飯が好きなだけなのに…。",
            "妻からは『バニーガール狂い』扱いされてるんだ…。",
            "\\!…本当に飯が旨いだけなのに。"
          ],
          "pointer": [
            0,
            1,
            2,
            3
          ],
          "meta": "101code"
        }
      ]
    },
    "7": {
      "0": [
        {
          "type": "text",
          "text": [
            "そういうお客さん",
            "やー…ここが特等席なのよ。",
            "はぁ…眼福、眼福…。"
          ],
          "pointer": [
            0,
            1,
            2
          ],
          "meta": "101code"
        },
        {
          "type": "text",
          "text": [
            "そういうお客さん",
            "絶対に譲らないわよ？"
          ],
          "pointer": [
            3,
            4
          ],
          "meta": "101code"
        },
        {
          "type": "text",
          "text": [
            "ラウラ",
            "い、いえ…お構いなく。"
          ],
          "pointer": [
            5,
            6
          ],
          "meta": "101code"
        }
      ]
    },
    "8": {
      "0": [
        {
          "type": "text",
          "text": [
            "バニーちゃん",
            "ご注文はメニューからお願いしまーす♥"
          ],
          "pointer": [
            0,
            1
          ],
          "meta": "101code"
        }
      ]
    },
    "9": {
      "0": [
        {
          "type": "text",
          "text": [
            "一段上の男",
            "あのバニーガールのピアノ…最高だよな。",
            "特に黒鍵のいぶし銀な輝きがさ…。",
            "\\!年季が入ってますます煌めいているよ…。"
          ],
          "pointer": [
            0,
            1,
            2,
            3
          ],
          "meta": "101code"
        }
      ]
    },
    "11": {
      "0": [
        {
          "type": "text",
          "text": [
            "癒されるお客さん",
            "いやー…ご飯も美味しいし、視界も華やかだし…。",
            "最高だわ。この店…。",
            "\\!５年くらい通ってるけど、飽きないわぁ…。"
          ],
          "pointer": [
            0,
            1,
            2,
            3
          ],
          "meta": "101code"
        }
      ]
    },
    "12": {
      "0": [
        {
          "type": "text",
          "text": [
            "バニー志望の女の子",
            "ねっ聞いて！ \\.私ね！",
            "おっきくなったら『バニーガール』になるの！",
            "\\!いっぱい『誘惑』して世界を私を好きな人で埋めつくすの！"
          ],
          "pointer": [
            0,
            1,
            2,
            3
          ],
          "meta": "101code"
        },
        {
          "type": "text",
          "text": [
            "バニー志望の女の子",
            "うっふん…♡",
            "\\!どうかな…\\.ちゃんと『誘惑』できてる…？\\!"
          ],
          "pointer": [
            6,
            7,
            8
          ],
          "meta": "101code"
        },
        {
          "type": "text_choice",
          "text": [
            "可愛いよ！",
            "セクシーだよ！"
          ],
          "pointer": 9
        },
        {
          "type": "text",
          "text": [
            "バニー志望の女の子",
            "あ、\\.ありがと…。",
            "\\!立派な『バニーガール』になるね…！"
          ],
          "pointer": [
            12,
            13,
            14
          ],
          "meta": "101code"
        },
        {
          "type": "text",
          "text": [
            "バニー志望の女の子",
            "せ、\\.『セクシー』…！！？",
            "\\.ふ、ふーん…\\.見る目あるじゃん…？",
            "\\!あなたを私の『ファン１号』にしてあげる！"
          ],
          "pointer": [
            18,
            19,
            20,
            21
          ],
          "meta": "101code"
        }
      ]
    },
    "13": {
      "0": [
        {
          "type": "text",
          "text": [
            "バニーガールさん",
            "おさわりは厳禁ですよー。"
          ],
          "pointer": [
            0,
            1
          ],
          "meta": "101code"
        },
        {
          "type": "text",
          "text": [
            "バニーガールさん",
            "（アフターは5000Gから応相談ですよー…。）"
          ],
          "pointer": [
            2,
            3
          ],
          "meta": "101code"
        },
        {
          "type": "text",
          "text": [
            "ラウラ",
            "いや、私には心に決めた人が…。"
          ],
          "pointer": [
            5,
            6
          ],
          "meta": "101code"
        },
        {
          "type": "text",
          "text": [
            "バニーガールさん",
            "やだ…初々しい…！",
            "お姉さん、応援しちゃうわ…！"
          ],
          "pointer": [
            7,
            8,
            9
          ],
          "meta": "101code"
        }
      ]
    },
    "17": {
      "0": [
        {
          "type": "text",
          "text": [
            "そういうお客さん",
            "やー…ここが特等席なのよ。",
            "はぁ…眼福、眼福…。"
          ],
          "pointer": [
            0,
            1,
            2
          ],
          "meta": "101code"
        },
        {
          "type": "text",
          "text": [
            "そういうお客さん",
            "絶対に譲らないわよ？"
          ],
          "pointer": [
            3,
            4
          ],
          "meta": "101code"
        },
        {
          "type": "text",
          "text": [
            "ラウラ",
            "い、いえ…お構いなく。"
          ],
          "pointer": [
            5,
            6
          ],
          "meta": "101code"
        }
      ]
    },
    "18": {
      "0": [
        {
          "type": "text",
          "text": [
            "そういうお客さん",
            "やー…ここが特等席なのよ。",
            "はぁ…眼福、眼福…。"
          ],
          "pointer": [
            0,
            1,
            2
          ],
          "meta": "101code"
        },
        {
          "type": "text",
          "text": [
            "そういうお客さん",
            "絶対に譲らないわよ？"
          ],
          "pointer": [
            3,
            4
          ],
          "meta": "101code"
        },
        {
          "type": "text",
          "text": [
            "ラウラ",
            "い、いえ…お構いなく。"
          ],
          "pointer": [
            5,
            6
          ],
          "meta": "101code"
        }
      ]
    },
    "19": {
      "0": [
        {
          "type": "text",
          "text": [
            "キャット",
            "\\SE[16]マスタぁー…。",
            "\\.追加で、\\.いつものをー……。"
          ],
          "pointer": [
            11,
            12,
            13
          ],
          "meta": "101code"
        },
        {
          "type": "text",
          "text": [
            "店主",
            "おいおい、\\.飲み過ぎなんじゃないか…？",
            "\\!たいして強い訳でもないんだからさぁ…。"
          ],
          "pointer": [
            16,
            17,
            18
          ],
          "meta": "101code"
        },
        {
          "type": "text",
          "text": [
            "キャット",
            "\\SE[45]いいんですよ…\\.今日はぁ…。",
            "\\!\\SE[16]ワタクシ頑張りましたしぃ…。"
          ],
          "pointer": [
            40,
            41,
            42
          ],
          "meta": "101code"
        },
        {
          "type": "text",
          "text": [
            "旦那様",
            "いつもそう言ってるし…。",
            "\\.今日は寝ちまわないでくれよ？"
          ],
          "pointer": [
            43,
            44,
            45
          ],
          "meta": "101code"
        },
        {
          "type": "text",
          "text": [
            "キャット",
            "\\SE[20]うふふぅ…\\.最高ですねぇ…。",
            "\\!\\SE[46]このために、生きてるって感じぃ……。"
          ],
          "pointer": [
            58,
            59,
            60
          ],
          "meta": "101code"
        },
        {
          "type": "text",
          "text": [
            "キャット",
            "\\SE[45]いつか、姐さんたちとも…。",
            "\\.一緒に飲んで…\\.みたいですねぇ…。"
          ],
          "pointer": [
            61,
            62,
            63
          ],
          "meta": "101code"
        },
        {
          "type": "text",
          "text": [
            "キャット",
            "\\SE[47]あれっ？ \\.おかしくないですか？",
            "\\.ワタクシはルナロアさんの『夢の中』に、いたはず…。",
            "\\!\\SE[48]いつの間にか『うたた寝』を…？"
          ],
          "pointer": [
            69,
            70,
            71,
            72
          ],
          "meta": "101code"
        },
        {
          "type": "text",
          "text": [
            "キャット",
            "\\SE[57]うぉ…ものすごい『ねむみ』がっ…。",
            "\\!\\SE[42]だ、だめです。\\.眠くない…\\.ねむくないですよぉ…。",
            "\\!\\SE[43]私は酔っていません…\\.酔ってませんよぉ…。"
          ],
          "pointer": [
            77,
            78,
            79,
            80
          ],
          "meta": "101code"
        },
        {
          "type": "text",
          "text": [
            "キャット",
            "\\SE[44]ねてません、\\.よぉ…。",
            "\\.わたしはっ…\\.\\SE[43]ぐぅ……。"
          ],
          "pointer": [
            82,
            83,
            84
          ],
          "meta": "101code"
        }
      ]
    }
  }
}